{
  "id": "1511787",
  "name": "bilibili",
  "font_family": "iconfont",
  "css_prefix_text": "icon-",
  "description": "",
  "glyphs": [
    {
      "icon_id": "8106217",
      "name": "delete",
      "font_class": "delete",
      "unicode": "e699",
      "unicode_decimal": 59033
    },
    {
      "icon_id": "1133697",
      "name": "up",
      "font_class": "less",
      "unicode": "e629",
      "unicode_decimal": 58921
    },
    {
      "icon_id": "5802479",
      "name": "放大镜",
      "font_class": "Magnifier",
      "unicode": "e62d",
      "unicode_decimal": 58925
    },
    {
      "icon_id": "1017253",
      "name": "iOS",
      "font_class": "ios",
      "unicode": "e676",
      "unicode_decimal": 58998
    }
  ]
}
